taken/__init__.py
taken-1.0.0.dist-info/METADATA
taken-1.0.0.dist-info/RECORD
taken-1.0.0.dist-info/WHEEL
taken-1.0.0.dist-info/top_level.txt
