Metadata-Version: 2.1
Name: taken
Version: 1.0.0
Summary: Random token generator
Home-page: https://github.com/amirmd76/taken.git
Author: AmirMohammad Dehghan
Author-email: dehghan@mit.edu
License: MIT
Platform: UNKNOWN
